message/message.py
schema_messages-0.1.5.dist-info/DESCRIPTION.rst
schema_messages-0.1.5.dist-info/METADATA
schema_messages-0.1.5.dist-info/metadata.json
schema_messages-0.1.5.dist-info/pbr.json
schema_messages-0.1.5.dist-info/RECORD
schema_messages-0.1.5.dist-info/top_level.txt
schema_messages-0.1.5.dist-info/WHEEL
schemamessages/__init__.py
schemamessages/exceptions.py
schemamessages/factory.py
schemamessages/message.py
schemamessages/packers.py
schemamessages/unpackers.py
schemamessages/utils.py
